MANIFEST.in
board_mrp_procurement_view.xml
company_view.xml
procurement_data.xml
procurement_demo.xml
procurement_view.xml
procurement_workflow.xml
setup.py
stock_orderpoint.xml
./__init__.py
./__openerp__.py
./company.py
./procurement.py
./schedulers.py
./wizard/__init__.py
./wizard/make_procurement_product.py
./wizard/mrp_procurement.py
./wizard/orderpoint_procurement.py
./wizard/schedulers_all.py
i18n/am.po
i18n/ar.po
i18n/bg.po
i18n/bs.po
i18n/ca.po
i18n/cs.po
i18n/da.po
i18n/de.po
i18n/es.po
i18n/es_CL.po
i18n/es_CR.po
i18n/es_EC.po
i18n/es_MX.po
i18n/es_VE.po
i18n/et.po
i18n/fi.po
i18n/fr.po
i18n/gl.po
i18n/hr.po
i18n/hu.po
i18n/id.po
i18n/it.po
i18n/ja.po
i18n/lt.po
i18n/mk.po
i18n/mn.po
i18n/nb.po
i18n/nl.po
i18n/pl.po
i18n/procurement.pot
i18n/pt.po
i18n/pt_BR.po
i18n/ro.po
i18n/ru.po
i18n/sl.po
i18n/sr.po
i18n/sr@latin.po
i18n/sv.po
i18n/tr.po
i18n/vi.po
i18n/zh_CN.po
i18n/zh_TW.po
images/compute_schedulers.jpeg
images/config_companies_sched.jpeg
images/minimum_stock_rules.jpeg
openerp_procurement.egg-info/PKG-INFO
openerp_procurement.egg-info/SOURCES.txt
openerp_procurement.egg-info/dependency_links.txt
openerp_procurement.egg-info/requires.txt
openerp_procurement.egg-info/top_level.txt
process/procurement_process.xml
security/ir.model.access.csv
security/procurement_security.xml
test/procurement.yml
wizard/make_procurement_view.xml
wizard/mrp_procurement_view.xml
wizard/orderpoint_procurement_view.xml
wizard/schedulers_all_view.xml